{
  "project_info": {
    "project_number": "619788247629",
    "project_id": "packing-314306",
    "storage_bucket": "packing-314306.appspot.com"
  },
  "client": [
    {
      "client_info": {
        "mobilesdk_app_id": "1:619788247629:android:eac3aa673222d884a93204",
        "android_client_info": {
          "package_name": "soulever.project"
        }
      },
      "oauth_client": [
        {
          "client_id": "619788247629-l7c6m3sfqkunnt9ef8ckbrujrfvllsk0.apps.googleusercontent.com",
          "client_type": 3
        }
      ],
      "api_key": [
        {
          "current_key": "AIzaSyBiKqiyWecE4uaFMscCD-WLQdWHqUpKki4"
        }
      ],
      "services": {
        "appinvite_service": {
          "other_platform_oauth_client": [
            {
              "client_id": "619788247629-l7c6m3sfqkunnt9ef8ckbrujrfvllsk0.apps.googleusercontent.com",
              "client_type": 3
            }
          ]
        }
      }
    }
  ],
  "configuration_version": "1"
}